Metadata-Version: 1.0
Name: aozora-cli
Version: 0.0.4
Summary: Aozora Bunko Command Line Tool
Home-page: https://github.com/aozorahack/aozora-cli
Author: Yasuhiro Kiyota
Author-email: yasuhiroki.duck@gmail.com
License: MIT
Platform: UNKNOWN
